btsbot/__init__.py
btsbot/alert_utils.py
btsbot/architectures.py
btsbot/from_HF.py
btsbot/inference_example.py
btsbot/to_HF.py
btsbot/train.py
btsbot/utils.py
btsbot/val.py
btsbot-2.0.6.dist-info/licenses/LICENSE
btsbot-2.0.6.dist-info/METADATA
btsbot-2.0.6.dist-info/WHEEL
btsbot-2.0.6.dist-info/top_level.txt
btsbot-2.0.6.dist-info/RECORD
