Metadata-Version: 2.4
Name: btsbot
Version: 2.0.6
Summary: Automatic supernova discovery with deep learning
Author-email: Nabeel Rehemtulla <nabeelr@u.northwestern.edu>
License: MIT
Project-URL: Homepage, https://github.com/nabeelre/BTSbot
Project-URL: Repository, https://github.com/nabeelre/BTSbot
Project-URL: Issues, https://github.com/nabeelre/BTSbot/issues
Keywords: astronomy,machine-learning,supernova,ztf,time-domain
Classifier: Intended Audience :: Science/Research
Classifier: Topic :: Scientific/Engineering :: Astronomy
Classifier: Programming Language :: Python :: 3
Classifier: Programming Language :: Python :: 3.8
Classifier: Programming Language :: Python :: 3.9
Classifier: Programming Language :: Python :: 3.10
Classifier: Programming Language :: Python :: 3.11
Classifier: Programming Language :: Python :: 3.12
Classifier: Programming Language :: Python :: 3.13
Requires-Python: >=3.8
License-File: LICENSE
Requires-Dist: numpy<3.0.0,>=1.24.3
Requires-Dist: pandas>=2.2.2
Requires-Dist: scipy>=1.10.0
Requires-Dist: torch>=2.0.0
Requires-Dist: torchvision>=0.15.0
Requires-Dist: scikit-learn>=1.5.0
Requires-Dist: Pillow>=9.0.0
Requires-Dist: opencv-python>=4.8.0
Requires-Dist: matplotlib>=3.7.1
Requires-Dist: tqdm>=4.66.4
Requires-Dist: requests>=2.32.3
Requires-Dist: astropy>=6.0.1
Requires-Dist: pymongo>=4.7.0
Requires-Dist: bson>=0.5.10
Requires-Dist: penquins>=2.4.0
Requires-Dist: timm>=0.9.0
Requires-Dist: umap-learn>=0.5.0
Requires-Dist: wandb>=0.15.0
Requires-Dist: datasets>=2.14.0
Requires-Dist: pyarrow>=10.0.0
Requires-Dist: fsspec>=2024.0.0
Requires-Dist: safetensors>=0.5.0
Requires-Dist: prettytable>=3.0.0
Requires-Dist: PyYAML>=6.0.0
Requires-Dist: protobuf>=4.0.0
Requires-Dist: huggingface-hub>=0.16.0
Provides-Extra: gpu
Requires-Dist: nvtx>=0.2.0; extra == "gpu"
Dynamic: license-file
